topsis_/__init__.py
topsis_/topsis.py
topsis_suhani_102313038-1.0.1.dist-info/licenses/LICENSE
topsis_suhani_102313038-1.0.1.dist-info/METADATA
topsis_suhani_102313038-1.0.1.dist-info/WHEEL
topsis_suhani_102313038-1.0.1.dist-info/entry_points.txt
topsis_suhani_102313038-1.0.1.dist-info/top_level.txt
topsis_suhani_102313038-1.0.1.dist-info/RECORD
