Metadata-Version: 2.4
Name: Topsis-Suhani-102313038
Version: 1.0.1
Summary: TOPSIS implementation for multi-criteria decision making
Author: Suhani Gupta
Author-email: suhani.work04@gmail.com
Classifier: Programming Language :: Python :: 3
Classifier: Operating System :: OS Independent
License-File: LICENSE
Requires-Dist: pandas
Requires-Dist: numpy
Dynamic: author
Dynamic: author-email
Dynamic: classifier
Dynamic: description
Dynamic: description-content-type
Dynamic: license-file
Dynamic: requires-dist
Dynamic: summary
